setup.py
keras_vgg_buddy/__init__.py
keras_vgg_buddy/imagenet.py
keras_vgg_buddy/img_utils.py
keras_vgg_buddy/models.py
keras_vgg_buddy.egg-info/PKG-INFO
keras_vgg_buddy.egg-info/SOURCES.txt
keras_vgg_buddy.egg-info/dependency_links.txt
keras_vgg_buddy.egg-info/requires.txt
keras_vgg_buddy.egg-info/top_level.txt