Metadata-Version: 1.0
Name: keras-vgg-buddy
Version: 0.1.1
Summary: Your pal when you want some VGG16 with your Keras.
Home-page: https://github.com/awentzonline/keras-vgg-buddy/
Author: Adam Wentz
Author-email: adam@adamwentz.com
License: UNKNOWN
Platform: UNKNOWN
